imperva_sdk/ADCUploader.py
imperva_sdk/Action.py
imperva_sdk/ActionSet.py
imperva_sdk/AgentConfiguration.py
imperva_sdk/AgentMonitoringRule.py
imperva_sdk/AssessmentPolicy.py
imperva_sdk/AssessmentScan.py
imperva_sdk/AssessmentTest.py
imperva_sdk/ClassificationProfile.py
imperva_sdk/ClassificationScan.py
imperva_sdk/CloudAccount.py
imperva_sdk/DBAuditReport.py
imperva_sdk/DBConnection.py
imperva_sdk/DataEnrichmentPolicy.py
imperva_sdk/DataType.py
imperva_sdk/DbApplication.py
imperva_sdk/DbAuditPolicy.py
imperva_sdk/DbSecurityPolicy.py
imperva_sdk/DbService.py
imperva_sdk/DiscoveryScan.py
imperva_sdk/Export.py
imperva_sdk/HttpProtocolSignaturesPolicy.py
imperva_sdk/Import.py
imperva_sdk/IpEntry.py
imperva_sdk/IpGroup.py
imperva_sdk/KrpRule.py
imperva_sdk/LookupDataSet.py
imperva_sdk/LookupDataType.py
imperva_sdk/MxConnection.py
imperva_sdk/ParameterTypeGlobalObject.py
imperva_sdk/ServerGroup.py
imperva_sdk/Site.py
imperva_sdk/SwaggerJsonFile.py
imperva_sdk/TableGroup.py
imperva_sdk/Tag.py
imperva_sdk/TrpRule.py
imperva_sdk/WebApplication.py
imperva_sdk/WebApplicationCustomPolicy.py
imperva_sdk/WebProfilePolicy.py
imperva_sdk/WebService.py
imperva_sdk/WebServiceCustomPolicy.py
imperva_sdk/__init__.py
imperva_sdk/core.py
imperva_sdk-0.2.0.dist-info/DESCRIPTION.rst
imperva_sdk-0.2.0.dist-info/METADATA
imperva_sdk-0.2.0.dist-info/RECORD
imperva_sdk-0.2.0.dist-info/WHEEL
imperva_sdk-0.2.0.dist-info/metadata.json
imperva_sdk-0.2.0.dist-info/top_level.txt
